LICENSE
MANIFEST.in
README.md
requirements.txt
setup.py
onnx_opcounter/__init__.py
onnx_opcounter/cli.py
onnx_opcounter/onnx_opcounter.py
onnx_opcounter.egg-info/PKG-INFO
onnx_opcounter.egg-info/SOURCES.txt
onnx_opcounter.egg-info/dependency_links.txt
onnx_opcounter.egg-info/entry_points.txt
onnx_opcounter.egg-info/not-zip-safe
onnx_opcounter.egg-info/requires.txt
onnx_opcounter.egg-info/top_level.txt