Metadata-Version: 1.0
Name: onnx-opcounter
Version: 0.0.3
Summary: ONNX flops / params counter
Home-page: UNKNOWN
Author: Grigory Malivenko
Author-email: nerox8664@gmail.com
License: UNKNOWN
Platform: UNKNOWN
